lazy_table/__init__.py
lazy_table/_lazy_table.py
lazy_table/artists/__init__.py
lazy_table/artists/_console.py
lazy_table-0.2.1.dist-info/LICENSE
lazy_table-0.2.1.dist-info/METADATA
lazy_table-0.2.1.dist-info/WHEEL
lazy_table-0.2.1.dist-info/top_level.txt
lazy_table-0.2.1.dist-info/RECORD
