Metadata-Version: 2.1
Name: lazy-table
Version: 0.2.1
Summary: A python-tabulate wrapper for producing tables from generators
Home-page: https://github.com/parsiad/lazy-table
Author: Parsiad Azimzadeh
Author-email: parsiad.azimzadeh@gmail.com
License: UNKNOWN
Project-URL: Bug Tracker, https://github.com/parsiad/lazy-table/issues
Platform: UNKNOWN
Classifier: Programming Language :: Python :: 3
Classifier: License :: OSI Approved :: MIT License
Classifier: Operating System :: OS Independent
Requires-Python: >=3.6
License-File: LICENSE
Requires-Dist: tabulate
